dynamic_logging/__init__.py
dynamic_logging/admin.py
dynamic_logging/apps.py
dynamic_logging/handlers.py
dynamic_logging/models.py
dynamic_logging/propagator.py
dynamic_logging/scheduler.py
dynamic_logging/settings.py
dynamic_logging/signals.py
dynamic_logging/tests.py
dynamic_logging/widgets.py
dynamic_logging/migrations/0001_initial.py
dynamic_logging/migrations/__init__.py
dynamic_logging/static/admin/css/dynamic_logging.css
dynamic_logging/static/admin/js/jquerymy-1.2.8.min.js
dynamic_logging/static/admin/js/logging_widget.js
dynamic_logging/static/admin/js/minimal.js
dynamic_logging/templates/admin/dynamic_logging/app_index.html
dynamic_logging/templates/admin/dynamic_logging/config/change_list.html
dynamic_logging/templates/dynamic_logging/display_config.html
dynamic_logging/templatetags/__init__.py
dynamic_logging/templatetags/dynamic_logging.py
django_dynamic_logging-2.0.0.dist-info/LICENSE
django_dynamic_logging-2.0.0.dist-info/METADATA
django_dynamic_logging-2.0.0.dist-info/WHEEL
django_dynamic_logging-2.0.0.dist-info/top_level.txt
django_dynamic_logging-2.0.0.dist-info/RECORD
