Metadata-Version: 2.1
Name: django-dynamic-logging
Version: 2.0.0
Summary: django app to manager logging in runtime system
Home-page: https://github.com/Yupeek/django-dynamic-logging
Author: Darius BERNARD
Author-email: darius@yupeek.com
License: GNU GENERAL PUBLIC LICENSE
Keywords: django logging dynamic handlers logger
Platform: UNKNOWN
Classifier: Development Status :: 4 - Beta
Classifier: Intended Audience :: Developers
Classifier: License :: OSI Approved :: GNU General Public License v3 (GPLv3)
Classifier: Programming Language :: Python :: 2
Classifier: Programming Language :: Python :: 2.7
Classifier: Programming Language :: Python :: 3
Classifier: Programming Language :: Python :: 3.3
Classifier: Programming Language :: Python :: 3.4
Classifier: Programming Language :: Python :: 3.5
Classifier: Operating System :: OS Independent
Classifier: Topic :: Software Development :: Libraries
Classifier: Topic :: Utilities
Classifier: Environment :: Web Environment
Classifier: Framework :: Django
Requires-Dist: pytz
